<?xml version="1.0" encoding="UTF-8"?>

<taxML xmlns="http://www.chinatax.gov.cn/dataspec/" xmlns:xsi="http://www.w3.org/2001/XMLSchema-instance" xsi:type="ShbxfQuerySbycjgResponse" xmlbh="" bbh="V1.0" xmlmc="" xsi:schemaLocation="http://www.chinatax.gov.cn/dataspec/TaxMLBw_GSSB_SB_00015_Response_V1.0.xsd">
	<SbcljgList>
		  <SbcljgResponse>
			  <sbcljgDm>1</sbcljgDm>
			  <sbsbyy></sbsbyy>
			  <yzpzxhList>
				  <yzpzxhResponse>
					  <yzpzxh>10000000000000004985</yzpzxh>
					  <sbzt>N</sbzt>
					  <sbmxList>
						<sbmxResponse><sblsh>123456</sblsh><xxh>1</xxh><sbjbjgDm>41019910</sbjbjgDm></sbmxResponse>
					  </sbmxList>
				  </yzpzxhResponse>
				  <yzpzxhResponse>
					  <yzpzxh>10000000000000007952</yzpzxh>
					  <sbzt>Y</sbzt>
					  <sbmxList>
						  <sbmxResponse><sblsh>4c4a74bc209b4c41aee431af9d70267b</sblsh><xxh>0</xxh><sbjbjgDm>41019910</sbjbjgDm></sbmxResponse>
						  <sbmxResponse><sblsh>ed47ef5b50ff439c87c9f24283abf25a</sblsh><xxh>0</xxh><sbjbjgDm>41019910</sbjbjgDm></sbmxResponse>
					  </sbmxList>
				  </yzpzxhResponse>
			  </yzpzxhList>
		  </SbcljgResponse>
	  </SbcljgList>
</taxML>